cryptrand/__init__.py
cryptorand-0.1.0.dist-info/LICENSE
cryptorand-0.1.0.dist-info/METADATA
cryptorand-0.1.0.dist-info/WHEEL
cryptorand-0.1.0.dist-info/top_level.txt
cryptorand-0.1.0.dist-info/RECORD
