Metadata-Version: 2.1
Name: cryptorand
Version: 0.1.0
Summary: A small module for crytp
Home-page: UNKNOWN
Author: BUS410
License: UNKNOWN
Platform: UNKNOWN
Requires-Python: >=3.6
